watchpoints/__init__.py
watchpoints/ast_monkey.py
watchpoints/util.py
watchpoints/watch.py
watchpoints/watch_element.py
watchpoints/watch_print.py
watchpoints-0.2.5.dist-info/LICENSE
watchpoints-0.2.5.dist-info/METADATA
watchpoints-0.2.5.dist-info/NOTICE.txt
watchpoints-0.2.5.dist-info/WHEEL
watchpoints-0.2.5.dist-info/top_level.txt
watchpoints-0.2.5.dist-info/RECORD
