Metadata-Version: 2.1
Name: watchpoints
Version: 0.2.5
Summary: watchpoints monitors read and write on variables
Home-page: https://github.com/gaogaotiantian/watchpoints
Author: Tian Gao
Author-email: gaogaotiantian@hotmail.com
License: UNKNOWN
Platform: UNKNOWN
Classifier: Development Status :: 4 - Beta
Classifier: Programming Language :: Python :: 3.6
Classifier: Programming Language :: Python :: 3.7
Classifier: Programming Language :: Python :: 3.8
Classifier: Programming Language :: Python :: 3.9
Classifier: Programming Language :: Python :: 3.10
Classifier: Intended Audience :: Developers
Classifier: License :: OSI Approved :: Apache Software License
Classifier: Operating System :: OS Independent
Requires-Python: >=3.6
